setup.py
waterfly/__init__.py
waterfly.egg-info/PKG-INFO
waterfly.egg-info/SOURCES.txt
waterfly.egg-info/dependency_links.txt
waterfly.egg-info/requires.txt
waterfly.egg-info/top_level.txt