Metadata-Version: 2.1
Name: waterfly
Version: 14.7.2023.22.16
Summary: Waterfly is a powerful new AI tool to create Firefly URLs, process images, and draw on images.
Author: Igor_Shapovalov_Andrejovich
Author-email: igor.shapovalov.andrejovich@gmail.com
